autoenv_tool/__init__.py
autoenv_tool/cli.py
autoenv_tool/utils/__init__.py
autoenv_tool/utils/env.py
tests/__init__.py
tests/test_autoenv.py
utils/__init__.py
utils/env.py
autoenv_tool-0.6.dist-info/METADATA
autoenv_tool-0.6.dist-info/WHEEL
autoenv_tool-0.6.dist-info/entry_points.txt
autoenv_tool-0.6.dist-info/top_level.txt
autoenv_tool-0.6.dist-info/RECORD
